Workbook

Sheet Raw Data
A1: Order ID | B1: Date | C1: Customer ID | D1: Customer Name | E1: Country | F1: Product | G1: Category | H1: Quantity | I1: Unit Price | J1: Discount (%) | K1: Revenue | L1: Payment Method
A2: ORD-00001 | B2: 44928 | C2: CUST-0139 | D2: Michael Kim | E2: Turkey | F2: Cotton T-Shirt | G2: Clothing | H2: 1 | I2: 18.74 | J2: 0.1 | K2: =H2*I2*(1-J2) | L2: PayPal
A3: ORD-00002 | B3: 44928 | C3: CUST-0147 | D3: Hans Schmidt | E3: France | F3: Wool Scarf | G3: Clothing | H3: 2 | I3: 20.8 | J3: 0.2 | K3: =H3*I3*(1-J3) | L3: Bank Transfer
A4: ORD-00003 | B4: 44931 | C4: CUST-0064 | D4: Charlotte Fischer | E4: Turkey | F4: Wireless Mouse | G4: Electronics | H4: 1 | I4: 22.79 | J4: 0.05 | K4: =H4*I4*(1-J4) | L4: Credit Card
A5: ORD-00004 | B5: 44931 | C5: CUST-0136 | D5: Amelia Wilson | E5: Canada | F5: Jump Rope | G5: Sports | H5: 3 | I5: 19.21 | J5: 0.05 | K5: =H5*I5*(1-J5) | L5: Credit Card
A6: ORD-00005 | B6: 44934 | C6: CUST-0131 | D6: Scarlett Rodriguez | E6: USA | F6: Business Strategy | G6: Books | H6: 2 | I6: 31.22 | J6: 0 | K6: =H6*I6*(1-J6) | L6: PayPal
A7: ORD-00006 | B7: 44936 | C7: CUST-0086 | D7: Sophie Miller | E7: USA | F7: Power Bank | G7: Electronics | H7: 3 | I7: 53.95 | J7: 0 | K7: =H7*I7*(1-J7) | L7: Credit Card
A8: ORD-00007 | B8: 44938 | C8: CUST-0042 | D8: Sarah Lefebvre | E8: Germany | F8: Kitchen Organizer | G8: Home & Garden | H8: 3 | I8: 33.07 | J8: 0.1 | K8: =H8*I8*(1-J8) | L8: Credit Card
A9: ORD-00008 | B9: 44939 | C9: CUST-0135 | D9: Michael Roy | E9: France | F9: Jump Rope | G9: Sports | H9: 1 | I9: 16.68 | J9: 0.2 | K9: =H9*I9*(1-J9) | L9: Bank Transfer
A10: ORD-00009 | B10: 44943 | C10: CUST-0062 | D10: Mehmet Weber | E10: USA | F10: Smartphone Case | G10: Electronics | H10: 2 | I10: 21.87 | J10: 0.1 | K10: =H10*I10*(1-J10) | L10: Bank Transfer
A11: ORD-00010 | B11: 44943 | C11: CUST-0067 | D11: Owen Demir | E11: UK | F11: Throw Pillow | G11: Home & Garden | H11: 2 | I11: 26.57 | J11: 0 | K11: =H11*I11*(1-J11) | L11: Credit Card
A12: ORD-00011 | B12: 44948 | C12: CUST-0069 | D12: Emma Moreau | E12: Germany | F12: Plant Pot Set | G12: Home & Garden | H12: 2 | I12: 26.75 | J12: 0.2 | K12: =H12*I12*(1-J12) | L12: Credit Card
A13: ORD-00012 | B13: 44949 | C13: CUST-0038 | D13: Scarlett Moreau | E13: UK | F13: Plant Pot Set | G13: Home & Garden | H13: 3 | I13: 34.35 | J13: 0.15 | K13: =H13*I13*(1-J13) | L13: Bank Transfer
... A551: ORD-00550 | B551: 45657 | C551: CUST-0114 | D551: Lucas Wilson | E551: Turkey | F551: Travel Photography | G551: Books | H551: 5 | I551: 39.34 | J551: 0.1 | K551: =H551*I551*(1-J551) | L551: PayPal

Sheet Product Performance
A1: Product | B1: Category | C1: Total Revenue | D1: Total Orders | E1: Avg Order Value | F1: Return Rate
A2: Running Shoes | B2: Clothing | C2: =SUMPRODUCT(('Raw Data'!H2:H551*'Raw Data'!I2:I551*(1-'Raw Data'!J2:J551))*('Raw Data'!F2:F551=A2)) | D2: =COUNTIF('Raw Data'!F2:F551,A2) | E2: =IF(D2>0,C2/D2,0) | F2: 0.028
A3: Winter Jacket | B3: Clothing | C3: =SUMPRODUCT(('Raw Data'!H2:H551*'Raw Data'!I2:I551*(1-'Raw Data'!J2:J551))*('Raw Data'!F2:F551=A3)) | D3: =COUNTIF('Raw Data'!F2:F551,A3) | E3: =IF(D3>0,C3/D3,0) | F3: 0.027
A4: Wireless Headphones | B4: Electronics | C4: =SUMPRODUCT(('Raw Data'!H2:H551*'Raw Data'!I2:I551*(1-'Raw Data'!J2:J551))*('Raw Data'!F2:F551=A4)) | D4: =COUNTIF('Raw Data'!F2:F551,A4) | E4: =IF(D4>0,C4/D4,0) | F4: 0.047
A5: Fitness Tracker | B5: Sports | C5: =SUMPRODUCT(('Raw Data'!H2:H551*'Raw Data'!I2:I551*(1-'Raw Data'!J2:J551))*('Raw Data'!F2:F551=A5)) | D5: =COUNTIF('Raw Data'!F2:F551,A5) | E5: =IF(D5>0,C5/D5,0) | F5: 0.047
A6: Denim Jeans | B6: Clothing | C6: =SUMPRODUCT(('Raw Data'!H2:H551*'Raw Data'!I2:I551*(1-'Raw Data'!J2:J551))*('Raw Data'!F2:F551=A6)) | D6: =COUNTIF('Raw Data'!F2:F551,A6) | E6: =IF(D6>0,C6/D6,0) | F6: 0.062
A7: Gym Bag | B7: Sports | C7: =SUMPRODUCT(('Raw Data'!H2:H551*'Raw Data'!I2:I551*(1-'Raw Data'!J2:J551))*('Raw Data'!F2:F551=A7)) | D7: =COUNTIF('Raw Data'!F2:F551,A7) | E7: =IF(D7>0,C7/D7,0) | F7: 0.05
A8: Laptop Stand | B8: Electronics | C8: =SUMPRODUCT(('Raw Data'!H2:H551*'Raw Data'!I2:I551*(1-'Raw Data'!J2:J551))*('Raw Data'!F2:F551=A8)) | D8: =COUNTIF('Raw Data'!F2:F551,A8) | E8: =IF(D8>0,C8/D8,0) | F8: 0.039
A9: Bluetooth Speaker | B9: Electronics | C9: =SUMPRODUCT(('Raw Data'!H2:H551*'Raw Data'!I2:I551*(1-'Raw Data'!J2:J551))*('Raw Data'!F2:F551=A9)) | D9: =COUNTIF('Raw Data'!F2:F551,A9) | E9: =IF(D9>0,C9/D9,0) | F9: 0.029
A10: Leather Belt | B10: Clothing | C10: =SUMPRODUCT(('Raw Data'!H2:H551*'Raw Data'!I2:I551*(1-'Raw Data'!J2:J551))*('Raw Data'!F2:F551=A10)) | D10: =COUNTIF('Raw Data'!F2:F551,A10) | E10: =IF(D10>0,C10/D10,0) | F10: 0.078
A11: Wall Clock | B11: Home & Garden | C11: =SUMPRODUCT(('Raw Data'!H2:H551*'Raw Data'!I2:I551*(1-'Raw Data'!J2:J551))*('Raw Data'!F2:F551=A11)) | D11: =COUNTIF('Raw Data'!F2:F551,A11) | E11: =IF(D11>0,C11/D11,0) | F11: 0.021
A12: Wool Scarf | B12: Clothing | C12: =SUMPRODUCT(('Raw Data'!H2:H551*'Raw Data'!I2:I551*(1-'Raw Data'!J2:J551))*('Raw Data'!F2:F551=A12)) | D12: =COUNTIF('Raw Data'!F2:F551,A12) | E12: =IF(D12>0,C12/D12,0) | F12: 0.078
A13: Data Science Handbook | B13: Books | C13: =SUMPRODUCT(('Raw Data'!H2:H551*'Raw Data'!I2:I551*(1-'Raw Data'!J2:J551))*('Raw Data'!F2:F551=A13)) | D13: =COUNTIF('Raw Data'!F2:F551,A13) | E13: =IF(D13>0,C13/D13,0) | F13: 0.037
A14: Power Bank | B14: Electronics | C14: =SUMPRODUCT(('Raw Data'!H2:H551*'Raw Data'!I2:I551*(1-'Raw Data'!J2:J551))*('Raw Data'!F2:F551=A14)) | D14: =COUNTIF('Raw Data'!F2:F551,A14) | E14: =IF(D14>0,C14/D14,0) | F14: 0.028
A15: Python Programming | B15: Books | C15: =SUMPRODUCT(('Raw Data'!H2:H551*'Raw Data'!I2:I551*(1-'Raw Data'!J2:J551))*('Raw Data'!F2:F551=A15)) | D15: =COUNTIF('Raw Data'!F2:F551,A15) | E15: =IF(D15>0,C15/D15,0) | F15: 0.046
A16: Wireless Mouse | B16: Electronics | C16: =SUMPRODUCT(('Raw Data'!H2:H551*'Raw Data'!I2:I551*(1-'Raw Data'!J2:J551))*('Raw Data'!F2:F551=A16)) | D16: =COUNTIF('Raw Data'!F2:F551,A16) | E16: =IF(D16>0,C16/D16,0) | F16: 0.02
A17: Plant Pot Set | B17: Home & Garden | C17: =SUMPRODUCT(('Raw Data'!H2:H551*'Raw Data'!I2:I551*(1-'Raw Data'!J2:J551))*('Raw Data'!F2:F551=A17)) | D17: =COUNTIF('Raw Data'!F2:F551,A17) | E17: =IF(D17>0,C17/D17,0) | F17: 0.025
A18: Business Strategy | B18: Books | C18: =SUMPRODUCT(('Raw Data'!H2:H551*'Raw Data'!I2:I551*(1-'Raw Data'!J2:J551))*('Raw Data'!F2:F551=A18)) | D18: =COUNTIF('Raw Data'!F2:F551,A18) | E18: =IF(D18>0,C18/D18,0) | F18: 0.021
A19: Kitchen Organizer | B19: Home & Garden | C19: =SUMPRODUCT(('Raw Data'!H2:H551*'Raw Data'!I2:I551*(1-'Raw Data'!J2:J551))*('Raw Data'!F2:F551=A19)) | D19: =COUNTIF('Raw Data'!F2:F551,A19) | E19: =IF(D19>0,C19/D19,0) | F19: 0.033
A20: LED Desk Lamp | B20: Home & Garden | C20: =SUMPRODUCT(('Raw Data'!H2:H551*'Raw Data'!I2:I551*(1-'Raw Data'!J2:J551))*('Raw Data'!F2:F551=A20)) | D20: =COUNTIF('Raw Data'!F2:F551,A20) | E20: =IF(D20>0,C20/D20,0) | F20: 0.045
A21: Throw Pillow | B21: Home & Garden | C21: =SUMPRODUCT(('Raw Data'!H2:H551*'Raw Data'!I2:I551*(1-'Raw Data'!J2:J551))*('Raw Data'!F2:F551=A21)) | D21: =COUNTIF('Raw Data'!F2:F551,A21) | E21: =IF(D21>0,C21/D21,0) | F21: 0.067
A22: Travel Photography | B22: Books | C22: =SUMPRODUCT(('Raw Data'!H2:H551*'Raw Data'!I2:I551*(1-'Raw Data'!J2:J551))*('Raw Data'!F2:F551=A22)) | D22: =COUNTIF('Raw Data'!F2:F551,A22) | E22: =IF(D22>0,C22/D22,0) | F22: 0.05
A23: Cooking Masterclass | B23: Books | C23: =SUMPRODUCT(('Raw Data'!H2:H551*'Raw Data'!I2:I551*(1-'Raw Data'!J2:J551))*('Raw Data'!F2:F551=A23)) | D23: =COUNTIF('Raw Data'!F2:F551,A23) | E23: =IF(D23>0,C23/D23,0) | F23: 0.042
A24: Cotton T-Shirt | B24: Clothing | C24: =SUMPRODUCT(('Raw Data'!H2:H551*'Raw Data'!I2:I551*(1-'Raw Data'!J2:J551))*('Raw Data'!F2:F551=A24)) | D24: =COUNTIF('Raw Data'!F2:F551,A24) | E24: =IF(D24>0,C24/D24,0) | F24: 0.062
A25: USB-C Hub | B25: Electronics | C25: =SUMPRODUCT(('Raw Data'!H2:H551*'Raw Data'!I2:I551*(1-'Raw Data'!J2:J551))*('Raw Data'!F2:F551=A25)) | D25: =COUNTIF('Raw Data'!F2:F551,A25) | E25: =IF(D25>0,C25/D25,0) | F25: 0.022
A26: Water Bottle | B26: Sports | C26: =SUMPRODUCT(('Raw Data'!H2:H551*'Raw Data'!I2:I551*(1-'Raw Data'!J2:J551))*('Raw Data'!F2:F551=A26)) | D26: =COUNTIF('Raw Data'!F2:F551,A26) | E26: =IF(D26>0,C26/D26,0) | F26: 0.025
A27: Resistance Bands | B27: Sports | C27: =SUMPRODUCT(('Raw Data'!H2:H551*'Raw Data'!I2:I551*(1-'Raw Data'!J2:J551))*('Raw Data'!F2:F551=A27)) | D27: =COUNTIF('Raw Data'!F2:F551,A27) | E27: =IF(D27>0,C27/D27,0) | F27: 0.065
A28: Jump Rope | B28: Sports | C28: =SUMPRODUCT(('Raw Data'!H2:H551*'Raw Data'!I2:I551*(1-'Raw Data'!J2:J551))*('Raw Data'!F2:F551=A28)) | D28: =COUNTIF('Raw Data'!F2:F551,A28) | E28: =IF(D28>0,C28/D28,0) | F28: 0.029
A29: Yoga Mat | B29: Sports | C29: =SUMPRODUCT(('Raw Data'!H2:H551*'Raw Data'!I2:I551*(1-'Raw Data'!J2:J551))*('Raw Data'!F2:F551=A29)) | D29: =COUNTIF('Raw Data'!F2:F551,A29) | E29: =IF(D29>0,C29/D29,0) | F29: 0.036
A30: Smart Watch Band | B30: Electronics | C30: =SUMPRODUCT(('Raw Data'!H2:H551*'Raw Data'!I2:I551*(1-'Raw Data'!J2:J551))*('Raw Data'!F2:F551=A30)) | D30: =COUNTIF('Raw Data'!F2:F551,A30) | E30: =IF(D30>0,C30/D30,0) | F30: 0.044
A31: Smartphone Case | B31: Electronics | C31: =SUMPRODUCT(('Raw Data'!H2:H551*'Raw Data'!I2:I551*(1-'Raw Data'!J2:J551))*('Raw Data'!F2:F551=A31)) | D31: =COUNTIF('Raw Data'!F2:F551,A31) | E31: =IF(D31>0,C31/D31,0) | F31: 0.053
A32: Scented Candle | B32: Home & Garden | C32: =SUMPRODUCT(('Raw Data'!H2:H551*'Raw Data'!I2:I551*(1-'Raw Data'!J2:J551))*('Raw Data'!F2:F551=A32)) | D32: =COUNTIF('Raw Data'!F2:F551,A32) | E32: =IF(D32>0,C32/D32,0) | F32: 0.031
A33: Self-Help Guide | B33: Books | C33: =SUMPRODUCT(('Raw Data'!H2:H551*'Raw Data'!I2:I551*(1-'Raw Data'!J2:J551))*('Raw Data'!F2:F551=A33)) | D33: =COUNTIF('Raw Data'!F2:F551,A33) | E33: =IF(D33>0,C33/D33,0) | F33: 0.074

Sheet Customer Segmentation
A1: Customer ID | B1: Customer Name | C1: Total Orders | D1: Total Spent | E1: Avg Order Value | F1: First Purchase | G1: Last Purchase | H1: Segment
A2: CUST-0137 | B2: Mia Dupont | C2: 8 | D2: 1494.88 | E2: 186.86 | F2: 44991 | G2: 45617 | H2: VIP
A3: CUST-0043 | B3: Daniel Mueller | C3: 11 | D3: 1475.46 | E3: 134.13 | F3: 44988 | G3: 45555 | H3: VIP
A4: CUST-0001 | B4: Jean Davis | C4: 6 | D4: 842.85 | E4: 140.47 | F4: 45200 | G4: 45537 | H4: VIP
A5: CUST-0085 | B5: Noah Wilson | C5: 5 | D5: 842.59 | E5: 168.52 | F5: 45030 | G5: 45531 | H5: VIP
A6: CUST-0099 | B6: Hans Garcia | C6: 5 | D6: 788.28 | E6: 157.66 | F6: 44965 | G6: 45621 | H6: VIP
A7: CUST-0148 | B7: Pierre Clark | C7: 6 | D7: 756.12 | E7: 126.02 | F7: 44973 | G7: 45487 | H7: VIP
A8: CUST-0090 | B8: Aria Brown | C8: 5 | D8: 731.92 | E8: 146.38 | F8: 45072 | G8: 45596 | H8: VIP
A9: CUST-0023 | B9: Lucas Kaya | C9: 5 | D9: 689.77 | E9: 137.95 | F9: 44989 | G9: 45548 | H9: VIP
A10: CUST-0127 | B10: Sophie Lefebvre | C10: 6 | D10: 644.66 | E10: 107.44 | F10: 45007 | G10: 45567 | H10: VIP
A11: CUST-0145 | B11: Mason Schmidt | C11: 7 | D11: 636.27 | E11: 90.9 | F11: 45055 | G11: 45540 | H11: VIP
A12: CUST-0017 | B12: Jean Roy | C12: 2 | D12: 615.26 | E12: 307.63 | F12: 45146 | G12: 45420 | H12: VIP
A13: CUST-0012 | B13: Thomas Clark | C13: 5 | D13: 607.46 | E13: 121.49 | F13: 44993 | G13: 45526 | H13: VIP
... A146: CUST-0013 | B146: Daniel Miller | C146: 1 | D146: 10.7 | E146: 10.7 | F146: 45175 | G146: 45175 | H146: At Risk

Sheet Monthly Trends
A1: Month | B1: Orders | C1: Revenue | D1: Avg Order Value | E1: New Customers
A2: 44927 | B2: 17 | C2: 1148.99 | D2: 67.59 | E2: 17
A3: 44958 | B3: 18 | C3: 1756.24 | D3: 97.57 | E3: 15
A4: 44986 | B4: 28 | C4: 2412.45 | D4: 86.16 | E4: 19
A5: 45017 | B5: 17 | C5: 940 | D5: 55.29 | E5: 10
A6: 45047 | B6: 28 | C6: 2331.37 | D6: 83.26 | E6: 12
A7: 45078 | B7: 19 | C7: 1341.25 | D7: 70.59 | E7: 7
A8: 45108 | B8: 21 | C8: 1410.01 | D8: 67.14 | E8: 11
A9: 45139 | B9: 22 | C9: 2269.27 | D9: 103.15 | E9: 7
A10: 45170 | B10: 28 | C10: 1438.82 | D10: 51.39 | E10: 10
A11: 45200 | B11: 27 | C11: 1910.45 | D11: 70.76 | E11: 8
A12: 45231 | B12: 14 | C12: 736.12 | D12: 52.58 | E12: 2
A13: 45261 | B13: 21 | C13: 1248.38 | D13: 59.45 | E13: 9
... A25: 45627 | B25: 29 | C25: 2153.46 | D25: 74.26 | E25: 1
A200: Month | B200: Revenue | C200: Orders
A201: 44927 | B201: 1148.99 | C201: 17
A202: 44958 | B202: 1756.24 | C202: 18
A203: 44986 | B203: 2412.45 | C203: 28
A204: 45017 | B204: 940 | C204: 17
A205: 45047 | B205: 2331.37 | C205: 28
A206: 45078 | B206: 1341.25 | C206: 19
A207: 45108 | B207: 1410.01 | C207: 21
A208: 45139 | B208: 2269.27 | C208: 22
A209: 45170 | B209: 1438.82 | C209: 28
A210: 45200 | B210: 1910.45 | C210: 27
A211: 45231 | B211: 736.12 | C211: 14
A212: 45261 | B212: 1248.38 | C212: 21
... A224: 45627 | B224: 2153.46 | C224: 29

Sheet Dashboard
B2: E-Commerce Sales Analysis | 2023-2024
B3: Data Source: Internal E-Commerce Platform | 550+ Transactions | 6 Markets
B5: TOTAL REVENUE | D5: TOTAL ORDERS | F5: AVG ORDER VALUE | H5: UNIQUE CUSTOMERS | J5: TOP COUNTRY
B6: 44552.889 | D6: 550 | F6: 81.005252 | H6: 145 | J6: USA
B9: Revenue by Country | H9: Revenue by Category
B10: Country | C10: Revenue | D10: Orders | E10: Avg Order | F10: % Share | H10: Category | I10: Revenue | J10: Orders | K10: Avg Order | L10: % Share
B11: USA | C11: 16622.08 | D11: 206 | E11: 80.69 | F11: 0.3731 | H11: Clothing | I11: 15304.13 | J11: 127 | K11: 120.5 | L11: 0.3435
B12: Germany | C12: 8396.71 | D12: 94 | E12: 89.33 | F12: 0.1885 | H12: Electronics | I12: 10738.01 | J12: 128 | K12: 83.89 | L12: 0.241
B13: Turkey | C13: 6208.32 | D13: 64 | E13: 97.01 | F13: 0.1393 | H13: Sports | I13: 7290.98 | J13: 119 | K13: 61.27 | L13: 0.1636
B14: France | C14: 5378.52 | D14: 79 | E14: 68.08 | F14: 0.1207 | H14: Home & Garden | I14: 5719.69 | J14: 98 | K14: 58.36 | L14: 0.1284
B15: UK | C15: 5162.08 | D15: 71 | E15: 72.71 | F15: 0.1159 | H15: Books | I15: 5500.08 | J15: 78 | K15: 70.51 | L15: 0.1235
B16: Canada | C16: 2785.18 | D16: 36 | E16: 77.37 | F16: 0.0625
B19: Key Insights
B20: 1. Total revenue of $44,552.89 generated across 550 orders from 145 unique customers.
B21: 2. USA leads all markets with $16,622.08 in revenue (37.3% share).
B22: 3. 'Running Shoes' is the best-selling product by revenue.
B23: 4. Clothing is the top-performing category with $15,304.13 revenue.
B24: 5. Average order value is $81.01, indicating a healthy basket size.
B25: 6. Credit Card is the dominant payment method across all markets.

Sheet Country Analysis
A1: Country | B1: Revenue | C1: Orders | D1: Avg Order Value | E1: % of Total Revenue
A2: USA | B2: 16622.08 | C2: 206 | D2: 80.69 | E2: 0.3731
A3: Germany | B3: 8396.71 | C3: 94 | D3: 89.33 | E3: 0.1885
A4: Turkey | B4: 6208.32 | C4: 64 | D4: 97.01 | E4: 0.1393
A5: France | B5: 5378.52 | C5: 79 | D5: 68.08 | E5: 0.1207
A6: UK | B6: 5162.08 | C6: 71 | D6: 72.71 | E6: 0.1159
A7: Canada | B7: 2785.18 | C7: 36 | D7: 77.37 | E7: 0.0625
A10: Top 3 Products by Country
A11: Country | B11: Rank | C11: Product | D11: Revenue | E11: % Country Revenue
A12: USA | B12: 1 | C12: Running Shoes | D12: 2348.1 | E12: 0.1413
A13: USA | B13: 2 | C13: Winter Jacket | D13: 1584.32 | E13: 0.0953
A14: USA | B14: 3 | C14: Wireless Headphones | D14: 1425.79 | E14: 0.0858
A15: Germany | B15: 1 | C15: Winter Jacket | D15: 1235 | E15: 0.1471
A16: Germany | B16: 2 | C16: Laptop Stand | D16: 680.09 | E16: 0.081
A17: Germany | B17: 3 | C17: Denim Jeans | D17: 670.68 | E17: 0.0799
A18: Turkey | B18: 1 | C18: Running Shoes | D18: 1543.5 | E18: 0.2486
A19: Turkey | B19: 2 | C19: Wireless Headphones | D19: 885.55 | E19: 0.1426
A20: Turkey | B20: 3 | C20: Leather Belt | D20: 431.9 | E20: 0.0696
A21: France | B21: 1 | C21: Gym Bag | D21: 495.2 | E21: 0.0921
A22: France | B22: 2 | C22: Plant Pot Set | D22: 395.42 | E22: 0.0735
A23: France | B23: 3 | C23: Winter Jacket | D23: 379.92 | E23: 0.0706
... A29: Canada | B29: 3 | C29: Winter Jacket | D29: 265.09 | E29: 0.0952
A200: Country | B200: Revenue
A201: USA | B201: 16622.08
A202: Germany | B202: 8396.71
A203: Turkey | B203: 6208.32
A204: France | B204: 5378.52
A205: UK | B205: 5162.08
A206: Canada | B206: 2785.18
